magic_bi/__init__.py
magic_bi/fake_main.py
magic_bi/main.py
magic_bi/user.py
magic_bi/action/__init__.py
magic_bi/action/action.py
magic_bi/action/action_to_str.py
magic_bi/agent/__init__.py
magic_bi/agent/agent_manager.py
magic_bi/agent/agent_meta.py
magic_bi/agent/agent_type.py
magic_bi/agent/app_agent.py
magic_bi/agent/base_agent.py
magic_bi/agent/finetuned_llm_sql_agent.py
magic_bi/agent/general_llm_sql_agent.py
magic_bi/agent/memmory.py
magic_bi/agent/pandas_agent.py
magic_bi/agent/rag_agent.py
magic_bi/agent/sql_explorer_agent.py
magic_bi/agent/utils.py
magic_bi/app/__init__.py
magic_bi/app/app.py
magic_bi/app/app_api.py
magic_bi/app/app_manager.py
magic_bi/config/__init__.py
magic_bi/config/agent_config.py
magic_bi/config/base_config.py
magic_bi/config/elasticsearch_config.py
magic_bi/config/global_config.py
magic_bi/config/misc_config.py
magic_bi/config/model_config.py
magic_bi/config/neo4j_config.py
magic_bi/config/orm_config.py
magic_bi/config/oss_config.py
magic_bi/config/qdrant_config.py
magic_bi/config/rabbitmq_config.py
magic_bi/config/utils.py
magic_bi/config/web_config.py
magic_bi/data/__init__.py
magic_bi/data/data.py
magic_bi/data/data_connector.py
magic_bi/data/data_connector_manager.py
magic_bi/data/data_connector_schema.py
magic_bi/data/data_manager.py
magic_bi/data/dataset.py
magic_bi/data/dataset_manager.py
magic_bi/data/data_connector_knowledge/__init__.py
magic_bi/data/data_connector_knowledge/domain_knowledge.py
magic_bi/data/data_connector_knowledge/qa_template.py
magic_bi/data/data_connector_knowledge/table_column_description.py
magic_bi/data/data_connector_knowledge/table_description.py
magic_bi/data/video/__init__.py
magic_bi/data/video/video_frame.py
magic_bi/data/video/video_frame_cropper.py
magic_bi/data/video/video_process.py
magic_bi/db/__init__.py
magic_bi/db/elasticsearch_adapter.py
magic_bi/db/neo4j_adapter.py
magic_bi/db/qdrant_adapter.py
magic_bi/db/sql_orm.py
magic_bi/db/timescale_orm.py
magic_bi/doc/__init__.py
magic_bi-0.1.1.dist-info/METADATA
magic_bi-0.1.1.dist-info/WHEEL
magic_bi-0.1.1.dist-info/top_level.txt
magic_bi-0.1.1.dist-info/RECORD
